tsdk/__init__.py
tsdk/actions/__init__.py
tsdk/actions/action1.py
tsdk/common/__init__.py
tsdk/common/connector.py
tsdk/common/dbconfig.py
tsdk/common/dblogs.py
tsdk/common/dbmanager.py
tsdk/common/dbtasks.py
tsdk/common/logs.py
tsdk/common/sshcmd.py
tsdk/common/sshconfig.py
tsdk/common/tsdk_scheduler.py
tsdk/common/tsdk_server.py
tsdk/implementation/__init__.py
tsdk/logics/__init__.py
tsdk/logics/audits/__init__.py
tsdk/logics/audits/nr_basic_audit_v2/__init__.py
tsdk/logics/audits/nr_basic_audit_v2/module_main.py
tsdk/logics/system/__init__.py
tsdk_git-5.3.3.dist-info/METADATA
tsdk_git-5.3.3.dist-info/WHEEL
tsdk_git-5.3.3.dist-info/top_level.txt
tsdk_git-5.3.3.dist-info/RECORD
